zepl_logging/__init__.py
zepl_logging/logging.py
zepl_logging-1.1.0.dist-info/METADATA
zepl_logging-1.1.0.dist-info/WHEEL
zepl_logging-1.1.0.dist-info/top_level.txt
zepl_logging-1.1.0.dist-info/RECORD
