Metadata-Version: 2.1
Name: zepl-logging
Version: 1.1.0
Summary: Alternate Logging package for zepl
Home-page: https://github.com/usama2762/zepl_logging_client
Author: Usama Jamil
Author-email: usamajamil77@gmail.com
License: MIT
Platform: UNKNOWN
Classifier: License :: OSI Approved :: MIT License
Classifier: Programming Language :: Python :: 3
Classifier: Programming Language :: Python :: 3.7
Requires-Dist: requests
Requires-Dist: datetime
